{
    "Config": {
        "General": {
            "NUM_CUSTOMERS": 10,
            "NUM_NODES": 11,
            "MAX_COORD_KM": 100,
            "T_MAX_SYSTEM_H": 18.17759347763444,
            "TIME_WINDOW_SCALING_FACTOR": 1.5,
            "COORD_DISTRIBUTION": "multi-gaussian",
            "NUM_CLUSTERS": 3
        },
        "Vehicles": {
            "NUM_TRUCKS": 2,
            "NUM_DRONES": 2,
            "V_TRUCK_KM_H": 40.0,
            "V_DRONE_KM_H": 60.0,
            "CAPACITY_TRUCK": 200,
            "CAPACITY_DRONE": 50,
            "DRONE_TAKEOFF_MIN": 1.0,
            "DRONE_LANDING_MIN": 1.0,
            "SERVICE_TIME_MIN": 5.0,
            "DRONE_DURATION_H": 1.0
        },
        "Depot": {
            "id": 0,
            "coord": [
                50.0,
                50.0
            ],
            "time_window_h": [
                0.0,
                18.17759347763444
            ]
        }
    },
    "Nodes": [
        {
            "id": 1,
            "coord": [
                26.069340813227655,
                65.96922073426406
            ],
            "demand": 16,
            "type": "LINEHAUL",
            "tw_h": [
                9.80486110210785,
                10.974286765244903
            ]
        },
        {
            "id": 2,
            "coord": [
                66.53362688943523,
                39.05721745711819
            ],
            "demand": 41,
            "type": "LINEHAUL",
            "tw_h": [
                20.688878795502557,
                20.951583480970832
            ]
        },
        {
            "id": 3,
            "coord": [
                44.76950258164784,
                59.94756990837645
            ],
            "demand": -15,
            "type": "BACKHAUL",
            "tw_h": [
                5.403828493875521,
                5.428355017383301
            ]
        },
        {
            "id": 4,
            "coord": [
                81.34458858912939,
                25.968304027176696
            ],
            "demand": 18,
            "type": "LINEHAUL",
            "tw_h": [
                2.7996128026287312,
                2.825697426488508
            ]
        },
        {
            "id": 5,
            "coord": [
                64.54318469876235,
                37.882348800890064
            ],
            "demand": -40,
            "type": "BACKHAUL",
            "tw_h": [
                3.760568042000732,
                4.489909104883195
            ]
        },
        {
            "id": 6,
            "coord": [
                81.70988878219597,
                0.0
            ],
            "demand": 29,
            "type": "LINEHAUL",
            "tw_h": [
                23.747829849061226,
                26.827400673385455
            ]
        },
        {
            "id": 7,
            "coord": [
                70.43920637176612,
                46.06476764548027
            ],
            "demand": -18,
            "type": "BACKHAUL",
            "tw_h": [
                9.082237706958743,
                9.714555436891498
            ]
        },
        {
            "id": 8,
            "coord": [
                68.58235623043635,
                36.259928248283195
            ],
            "demand": 44,
            "type": "LINEHAUL",
            "tw_h": [
                16.591431081897102,
                17.156689694007895
            ]
        },
        {
            "id": 9,
            "coord": [
                71.2046468779207,
                37.659576321620555
            ],
            "demand": -10,
            "type": "BACKHAUL",
            "tw_h": [
                1.7652823338784378,
                3.3137341932762205
            ]
        },
        {
            "id": 10,
            "coord": [
                38.84184154701437,
                65.85040791286107
            ],
            "demand": -13,
            "type": "BACKHAUL",
            "tw_h": [
                14.813278941937996,
                14.976118931562317
            ]
        }
    ]
}