{
    "Config": {
        "General": {
            "NUM_CUSTOMERS": 75,
            "NUM_NODES": 76,
            "MAX_COORD_KM": 100,
            "T_MAX_SYSTEM_H": 284.0307400562817,
            "TIME_WINDOW_SCALING_FACTOR": 1.5,
            "COORD_DISTRIBUTION": "multi-gaussian",
            "NUM_CLUSTERS": 5
        },
        "Vehicles": {
            "NUM_TRUCKS": 1,
            "NUM_DRONES": 1,
            "V_TRUCK_KM_H": 40.0,
            "V_DRONE_KM_H": 60.0,
            "CAPACITY_TRUCK": 1000,
            "CAPACITY_DRONE": 50,
            "DRONE_TAKEOFF_MIN": 1.0,
            "DRONE_LANDING_MIN": 1.0,
            "SERVICE_TIME_MIN": 5.0,
            "DRONE_DURATION_H": 1.0
        },
        "Depot": {
            "id": 0,
            "coord": [
                0.0,
                0.0
            ],
            "time_window_h": [
                0.0,
                284.0307400562817
            ]
        }
    },
    "Nodes": [
        {
            "id": 1,
            "coord": [
                100.0,
                47.004448264836405
            ],
            "demand": 16,
            "type": "LINEHAUL",
            "tw_h": [
                6.525009945218179,
                10.569405945185867
            ]
        },
        {
            "id": 2,
            "coord": [
                11.875316084349823,
                63.268481103022644
            ],
            "demand": 6,
            "type": "LINEHAUL",
            "tw_h": [
                1.9651042169079975,
                3.600509055767931
            ]
        },
        {
            "id": 3,
            "coord": [
                43.99276170894824,
                43.711416695417235
            ],
            "demand": -4,
            "type": "BACKHAUL",
            "tw_h": [
                1.7360065849284965,
                1.7873393811202243
            ]
        },
        {
            "id": 4,
            "coord": [
                12.61364811930364,
                68.75432745755275
            ],
            "demand": 31,
            "type": "LINEHAUL",
            "tw_h": [
                6.8124071015704475,
                7.429498614616653
            ]
        },
        {
            "id": 5,
            "coord": [
                99.32271669017699,
                55.77414230118301
            ],
            "demand": -19,
            "type": "BACKHAUL",
            "tw_h": [
                7.464917395488017,
                13.816640060997019
            ]
        },
        {
            "id": 6,
            "coord": [
                13.463828899660403,
                61.60463401904159
            ],
            "demand": -20,
            "type": "BACKHAUL",
            "tw_h": [
                0.8581371723046152,
                3.8137206383397944
            ]
        },
        {
            "id": 7,
            "coord": [
                24.788358172568586,
                9.299506005042353
            ],
            "demand": 21,
            "type": "LINEHAUL",
            "tw_h": [
                3.2402678617689684,
                4.819001344062569
            ]
        },
        {
            "id": 8,
            "coord": [
                19.01716171526616,
                65.99998906041174
            ],
            "demand": 14,
            "type": "LINEHAUL",
            "tw_h": [
                17.68722298517045,
                18.774218675204192
            ]
        },
        {
            "id": 9,
            "coord": [
                97.73828450964466,
                60.87820361727102
            ],
            "demand": 46,
            "type": "LINEHAUL",
            "tw_h": [
                20.35383792413434,
                26.54849603058728
            ]
        },
        {
            "id": 10,
            "coord": [
                49.05168615727651,
                53.363300918931394
            ],
            "demand": 41,
            "type": "LINEHAUL",
            "tw_h": [
                1.7988318108769077,
                4.017509906422601
            ]
        },
        {
            "id": 11,
            "coord": [
                2.178757123758537,
                63.84562815712532
            ],
            "demand": -15,
            "type": "BACKHAUL",
            "tw_h": [
                16.810826192592426,
                21.232912480482113
            ]
        },
        {
            "id": 12,
            "coord": [
                20.67804742276951,
                71.45358814582579
            ],
            "demand": 41,
            "type": "LINEHAUL",
            "tw_h": [
                4.133068678498309,
                5.538189540150247
            ]
        },
        {
            "id": 13,
            "coord": [
                27.842341258360978,
                4.781217367369759
            ],
            "demand": 30,
            "type": "LINEHAUL",
            "tw_h": [
                18.602231870626113,
                20.641885514392754
            ]
        },
        {
            "id": 14,
            "coord": [
                24.034582232240265,
                7.467865822409628
            ],
            "demand": -36,
            "type": "BACKHAUL",
            "tw_h": [
                2.2501105805747637,
                2.4196706925593947
            ]
        },
        {
            "id": 15,
            "coord": [
                11.168883806836298,
                64.89443241235534
            ],
            "demand": -3,
            "type": "BACKHAUL",
            "tw_h": [
                18.02830523166159,
                19.593801704564246
            ]
        },
        {
            "id": 16,
            "coord": [
                43.46355179981445,
                43.97783991386707
            ],
            "demand": 17,
            "type": "LINEHAUL",
            "tw_h": [
                9.282635396572857,
                13.346502951822309
            ]
        },
        {
            "id": 17,
            "coord": [
                3.6197168680592995,
                15.284730802034623
            ],
            "demand": -22,
            "type": "BACKHAUL",
            "tw_h": [
                17.899188374991596,
                18.67755276981228
            ]
        },
        {
            "id": 18,
            "coord": [
                96.37009629939745,
                47.761366705745495
            ],
            "demand": -9,
            "type": "BACKHAUL",
            "tw_h": [
                20.823648625385424,
                26.728839469172367
            ]
        },
        {
            "id": 19,
            "coord": [
                97.88109636797684,
                52.11730074838954
            ],
            "demand": 37,
            "type": "LINEHAUL",
            "tw_h": [
                19.44597328344536,
                24.795800366604297
            ]
        },
        {
            "id": 20,
            "coord": [
                26.400835515658862,
                2.578015443752685
            ],
            "demand": -34,
            "type": "BACKHAUL",
            "tw_h": [
                14.235798894746178,
                14.354899254137548
            ]
        },
        {
            "id": 21,
            "coord": [
                7.781431374775413,
                18.19159352356118
            ],
            "demand": 32,
            "type": "LINEHAUL",
            "tw_h": [
                21.83067858940603,
                23.18368951725392
            ]
        },
        {
            "id": 22,
            "coord": [
                0.0,
                21.152360579542094
            ],
            "demand": -25,
            "type": "BACKHAUL",
            "tw_h": [
                8.432244328729029,
                9.425897184914952
            ]
        },
        {
            "id": 23,
            "coord": [
                44.9294700678687,
                49.42462710983788
            ],
            "demand": -37,
            "type": "BACKHAUL",
            "tw_h": [
                0.4055770486005077,
                2.9101987042704245
            ]
        },
        {
            "id": 24,
            "coord": [
                100.0,
                58.60490454292723
            ],
            "demand": 4,
            "type": "LINEHAUL",
            "tw_h": [
                14.960961060051796,
                17.51484503365153
            ]
        },
        {
            "id": 25,
            "coord": [
                5.637767069043882,
                70.31205582705302
            ],
            "demand": -10,
            "type": "BACKHAUL",
            "tw_h": [
                9.94792831870808,
                14.36769303582312
            ]
        },
        {
            "id": 26,
            "coord": [
                24.65650851279746,
                6.097759759025668
            ],
            "demand": 50,
            "type": "LINEHAUL",
            "tw_h": [
                3.442401156012717,
                4.310041717264861
            ]
        },
        {
            "id": 27,
            "coord": [
                100.0,
                46.51884900606274
            ],
            "demand": -42,
            "type": "BACKHAUL",
            "tw_h": [
                2.072929959322696,
                5.252753807673313
            ]
        },
        {
            "id": 28,
            "coord": [
                100.0,
                51.808699126915705
            ],
            "demand": 24,
            "type": "LINEHAUL",
            "tw_h": [
                21.18057534369703,
                26.35382602091481
            ]
        },
        {
            "id": 29,
            "coord": [
                25.563748352988704,
                19.96192294952735
            ],
            "demand": -21,
            "type": "BACKHAUL",
            "tw_h": [
                0.6960565968012062,
                2.7847784929670047
            ]
        },
        {
            "id": 30,
            "coord": [
                36.535946361083276,
                38.252617551135344
            ],
            "demand": 5,
            "type": "LINEHAUL",
            "tw_h": [
                15.799333625486405,
                17.86451546704201
            ]
        },
        {
            "id": 31,
            "coord": [
                6.7421965914375495,
                11.21451391923652
            ],
            "demand": 47,
            "type": "LINEHAUL",
            "tw_h": [
                6.923124489470392,
                7.218371188247409
            ]
        },
        {
            "id": 32,
            "coord": [
                94.11126895094556,
                53.949119431208025
            ],
            "demand": -17,
            "type": "BACKHAUL",
            "tw_h": [
                4.388873578912855,
                9.450631680800917
            ]
        },
        {
            "id": 33,
            "coord": [
                100.0,
                53.76163668206219
            ],
            "demand": -25,
            "type": "BACKHAUL",
            "tw_h": [
                1.1942824246719494,
                9.239524514224467
            ]
        },
        {
            "id": 34,
            "coord": [
                7.6505932155670635,
                9.438069367958121
            ],
            "demand": -40,
            "type": "BACKHAUL",
            "tw_h": [
                2.4658766990212238,
                3.0345405780594885
            ]
        },
        {
            "id": 35,
            "coord": [
                51.29600549884075,
                38.21858697017532
            ],
            "demand": -48,
            "type": "BACKHAUL",
            "tw_h": [
                13.821922966181088,
                15.559897848271905
            ]
        },
        {
            "id": 36,
            "coord": [
                45.10533561002406,
                56.08182069817106
            ],
            "demand": 48,
            "type": "LINEHAUL",
            "tw_h": [
                6.680565200136866,
                9.050855360842197
            ]
        },
        {
            "id": 37,
            "coord": [
                8.949640285732913,
                67.6298140415578
            ],
            "demand": 24,
            "type": "LINEHAUL",
            "tw_h": [
                7.904460359342464,
                12.875573406383353
            ]
        },
        {
            "id": 38,
            "coord": [
                22.839617052485877,
                0.8904864964077905
            ],
            "demand": -35,
            "type": "BACKHAUL",
            "tw_h": [
                15.479267947833653,
                16.368303193230577
            ]
        },
        {
            "id": 39,
            "coord": [
                35.233881535037625,
                44.690982236397765
            ],
            "demand": 8,
            "type": "LINEHAUL",
            "tw_h": [
                15.918348531438205,
                18.025946849487482
            ]
        },
        {
            "id": 40,
            "coord": [
                100.0,
                56.567014791897066
            ],
            "demand": 24,
            "type": "LINEHAUL",
            "tw_h": [
                3.568352399856564,
                3.7639633110361093
            ]
        },
        {
            "id": 41,
            "coord": [
                31.63740874073725,
                22.697126487062583
            ],
            "demand": -48,
            "type": "BACKHAUL",
            "tw_h": [
                23.280968474629326,
                25.74657479977741
            ]
        },
        {
            "id": 42,
            "coord": [
                100.0,
                53.55874211323211
            ],
            "demand": 14,
            "type": "LINEHAUL",
            "tw_h": [
                2.282029719624467,
                7.477632173094052
            ]
        },
        {
            "id": 43,
            "coord": [
                100.0,
                59.86526850877325
            ],
            "demand": -25,
            "type": "BACKHAUL",
            "tw_h": [
                18.841822039433175,
                26.658760760278568
            ]
        },
        {
            "id": 44,
            "coord": [
                99.01732353954357,
                56.58512136574987
            ],
            "demand": 33,
            "type": "LINEHAUL",
            "tw_h": [
                1.5520371244814646,
                2.6834264694985537
            ]
        },
        {
            "id": 45,
            "coord": [
                97.50901392348611,
                54.51660029271166
            ],
            "demand": -25,
            "type": "BACKHAUL",
            "tw_h": [
                9.41317477133123,
                14.463640975226632
            ]
        },
        {
            "id": 46,
            "coord": [
                12.20804304292399,
                13.973575074724577
            ],
            "demand": -22,
            "type": "BACKHAUL",
            "tw_h": [
                1.9849572774739723,
                2.9531974500105402
            ]
        },
        {
            "id": 47,
            "coord": [
                13.14429405356246,
                61.93798169857706
            ],
            "demand": 34,
            "type": "LINEHAUL",
            "tw_h": [
                18.112287051937283,
                20.233977865849152
            ]
        },
        {
            "id": 48,
            "coord": [
                99.90547312473493,
                50.49113296644645
            ],
            "demand": 47,
            "type": "LINEHAUL",
            "tw_h": [
                20.37660865194446,
                23.641536436606543
            ]
        },
        {
            "id": 49,
            "coord": [
                5.831613834925486,
                16.203789979899383
            ],
            "demand": 33,
            "type": "LINEHAUL",
            "tw_h": [
                20.001871218216365,
                20.495481381252045
            ]
        },
        {
            "id": 50,
            "coord": [
                32.77908698816684,
                6.264745273881708
            ],
            "demand": 2,
            "type": "LINEHAUL",
            "tw_h": [
                9.653640368808734,
                10.597683931582838
            ]
        },
        {
            "id": 51,
            "coord": [
                10.041332477814024,
                23.439987049489023
            ],
            "demand": -30,
            "type": "BACKHAUL",
            "tw_h": [
                17.036598001513806,
                18.725250213241193
            ]
        },
        {
            "id": 52,
            "coord": [
                13.569831786042169,
                63.43884539840377
            ],
            "demand": -47,
            "type": "BACKHAUL",
            "tw_h": [
                1.7337254263987614,
                4.604455925630454
            ]
        },
        {
            "id": 53,
            "coord": [
                29.472882744380847,
                11.995828505503775
            ],
            "demand": 10,
            "type": "LINEHAUL",
            "tw_h": [
                20.05292933673676,
                21.704417441956984
            ]
        },
        {
            "id": 54,
            "coord": [
                4.34444371625183,
                22.4065886638581
            ],
            "demand": 49,
            "type": "LINEHAUL",
            "tw_h": [
                5.617279408221446,
                6.241042696112645
            ]
        },
        {
            "id": 55,
            "coord": [
                10.327625508550533,
                16.990647854010607
            ],
            "demand": 23,
            "type": "LINEHAUL",
            "tw_h": [
                21.269157989273,
                21.59095562476764
            ]
        },
        {
            "id": 56,
            "coord": [
                42.439745044169506,
                53.8225937601684
            ],
            "demand": 31,
            "type": "LINEHAUL",
            "tw_h": [
                22.894344438213906,
                24.908307930119975
            ]
        },
        {
            "id": 57,
            "coord": [
                6.938385104707993,
                59.82955057547759
            ],
            "demand": 45,
            "type": "LINEHAUL",
            "tw_h": [
                12.486658669479315,
                15.68538705293322
            ]
        },
        {
            "id": 58,
            "coord": [
                22.450089465554797,
                5.108436001155938
            ],
            "demand": 20,
            "type": "LINEHAUL",
            "tw_h": [
                16.347910239584877,
                17.36752414928318
            ]
        },
        {
            "id": 59,
            "coord": [
                33.76314904884117,
                10.40181751438493
            ],
            "demand": -14,
            "type": "BACKHAUL",
            "tw_h": [
                20.82144800106549,
                22.518279898230073
            ]
        },
        {
            "id": 60,
            "coord": [
                29.146049964718518,
                10.12942826720873
            ],
            "demand": -22,
            "type": "BACKHAUL",
            "tw_h": [
                21.98982461698126,
                23.497787720034673
            ]
        },
        {
            "id": 61,
            "coord": [
                11.365684149719236,
                14.222016770869706
            ],
            "demand": -13,
            "type": "BACKHAUL",
            "tw_h": [
                14.108191728513091,
                14.18565753089918
            ]
        },
        {
            "id": 62,
            "coord": [
                30.527895900267325,
                10.294739526510845
            ],
            "demand": 25,
            "type": "LINEHAUL",
            "tw_h": [
                21.80813358565701,
                22.361945018838224
            ]
        },
        {
            "id": 63,
            "coord": [
                10.681176125785719,
                58.75498414141352
            ],
            "demand": -30,
            "type": "BACKHAUL",
            "tw_h": [
                5.41359133634477,
                5.634084847524009
            ]
        },
        {
            "id": 64,
            "coord": [
                37.28965273856046,
                40.42210590025373
            ],
            "demand": 23,
            "type": "LINEHAUL",
            "tw_h": [
                14.910344622236831,
                16.437779818753768
            ]
        },
        {
            "id": 65,
            "coord": [
                41.93414225362959,
                50.75575067374693
            ],
            "demand": 45,
            "type": "LINEHAUL",
            "tw_h": [
                15.66077189721996,
                19.677430058501574
            ]
        },
        {
            "id": 66,
            "coord": [
                30.374984501521617,
                16.12310481146104
            ],
            "demand": -47,
            "type": "BACKHAUL",
            "tw_h": [
                22.602574548142986,
                24.673905842596877
            ]
        },
        {
            "id": 67,
            "coord": [
                10.00169747644513,
                67.13538747936282
            ],
            "demand": -27,
            "type": "BACKHAUL",
            "tw_h": [
                20.1240532445201,
                22.063714586812633
            ]
        },
        {
            "id": 68,
            "coord": [
                0.16079029952403356,
                20.818370472763906
            ],
            "demand": -42,
            "type": "BACKHAUL",
            "tw_h": [
                1.2761801571404598,
                2.477526356841528
            ]
        },
        {
            "id": 69,
            "coord": [
                12.03433733284875,
                68.66631993966655
            ],
            "demand": 21,
            "type": "LINEHAUL",
            "tw_h": [
                23.88282942643456,
                26.303242098617233
            ]
        },
        {
            "id": 70,
            "coord": [
                11.88626646662365,
                50.60398587244934
            ],
            "demand": -9,
            "type": "BACKHAUL",
            "tw_h": [
                21.583309002728456,
                23.788865200158018
            ]
        },
        {
            "id": 71,
            "coord": [
                32.528019119851024,
                11.686508568018148
            ],
            "demand": -43,
            "type": "BACKHAUL",
            "tw_h": [
                9.246299251214307,
                11.40316055359617
            ]
        },
        {
            "id": 72,
            "coord": [
                36.069592424959026,
                42.3690254905989
            ],
            "demand": -30,
            "type": "BACKHAUL",
            "tw_h": [
                1.4966915994798482,
                3.010166958997922
            ]
        },
        {
            "id": 73,
            "coord": [
                8.069403582879339,
                19.07252686950337
            ],
            "demand": -21,
            "type": "BACKHAUL",
            "tw_h": [
                16.700327622759364,
                16.827266235859565
            ]
        },
        {
            "id": 74,
            "coord": [
                13.444209524042087,
                22.805242207589323
            ],
            "demand": -47,
            "type": "BACKHAUL",
            "tw_h": [
                13.290806498727772,
                14.062582657718279
            ]
        },
        {
            "id": 75,
            "coord": [
                4.865760284177939,
                8.3445699578174
            ],
            "demand": -30,
            "type": "BACKHAUL",
            "tw_h": [
                5.284648598779454,
                5.578984033313644
            ]
        }
    ]
}