{
  "weights": {
    "cost": 0.0,
    "makespan": 1.0,
    "wait": 0.0
  },
  "objective": 0.34,
  "routes": [
    {
      "id": 1,
      "route": [
        0,
        3,
        4,
        11
      ],
      "arrival": [
        null,
        1.72,
        19.78,
        23.52
      ],
      "departure": [
        0.0,
        17.76,
        21.5,
        null
      ],
      "trips": [
        {
          "id": 1,
          "route": [
            3,
            8,
            11
          ],
          "arrival": [
            null,
            15.58,
            16.45
          ],
          "departure": [
            15.5,
            15.68,
            null
          ]
        }
      ]
    },
    {
      "id": 2,
      "route": [
        0,
        7,
        9,
        6,
        5,
        1,
        10,
        11
      ],
      "arrival": [
        null,
        1.55,
        3.74,
        7.2,
        9.39,
        11.38,
        17.22,
        20.2
      ],
      "departure": [
        0.0,
        1.63,
        5.37,
        7.28,
        10.21,
        15.43,
        19.51,
        null
      ],
      "trips": []
    }
  ]
}