{
  "weights": {
    "cost": 1.0,
    "makespan": 0.0,
    "wait": 0.0
  },
  "objective": 489.48,
  "routes": [
    {
      "id": 1,
      "route": [
        0,
        7,
        4,
        3,
        5,
        8,
        9,
        6,
        2,
        1,
        11
      ],
      "arrival": [
        null,
        9.08,
        9.99,
        10.66,
        15.16,
        16.59,
        22.56,
        23.75,
        24.61,
        25.56,
        27.99
      ],
      "departure": [
        0.0,
        9.17,
        10.07,
        14.53,
        15.24,
        20.56,
        22.64,
        23.83,
        24.69,
        25.64,
        null
      ],
      "trips": [
        {
          "id": 1,
          "route": [
            1,
            10,
            2
          ],
          "arrival": [
            null,
            24.27,
            24.68
          ],
          "departure": [
            23.89,
            24.37,
            null
          ]
        },
        {
          "id": 2,
          "route": [
            1,
            10,
            2
          ],
          "arrival": [
            null,
            24.27,
            24.68
          ],
          "departure": [
            23.89,
            24.37,
            null
          ]
        }
      ]
    }
  ]
}