{
    "Config": {
        "General": {
            "NUM_CUSTOMERS": 150,
            "NUM_NODES": 151,
            "MAX_COORD_KM": 100,
            "T_MAX_SYSTEM_H": 383.8630332717256,
            "TIME_WINDOW_SCALING_FACTOR": 1.5,
            "COORD_DISTRIBUTION": "uniform",
            "NUM_CLUSTERS": 0
        },
        "Vehicles": {
            "NUM_TRUCKS": 15,
            "NUM_DRONES": 15,
            "V_TRUCK_KM_H": 40.0,
            "V_DRONE_KM_H": 60.0,
            "CAPACITY_TRUCK": 1000,
            "CAPACITY_DRONE": 50,
            "DRONE_TAKEOFF_MIN": 1.0,
            "DRONE_LANDING_MIN": 1.0,
            "SERVICE_TIME_MIN": 5.0
        },
        "Depot": {
            "id": 0,
            "coord": [
                50.0,
                50.0
            ],
            "time_window_h": [
                0.0,
                383.8630332717256
            ]
        }
    },
    "Nodes": [
        {
            "id": 1,
            "coord": [
                14.792062434808473,
                22.829835699996647
            ],
            "demand": 2,
            "type": "LINEHAUL",
            "tw_h": [
                23.03906232467893,
                25.94711904152612
            ]
        },
        {
            "id": 2,
            "coord": [
                80.74933620503766,
                29.847457554008315
            ],
            "demand": 33,
            "type": "LINEHAUL",
            "tw_h": [
                17.565727073680414,
                18.1933630958575
            ]
        },
        {
            "id": 3,
            "coord": [
                18.57067421006168,
                77.21373073244318
            ],
            "demand": -9,
            "type": "BACKHAUL",
            "tw_h": [
                7.935415865196598,
                10.161108047753288
            ]
        },
        {
            "id": 4,
            "coord": [
                40.54395228285736,
                99.59045380032603
            ],
            "demand": 45,
            "type": "LINEHAUL",
            "tw_h": [
                19.36102595645908,
                19.424345180868496
            ]
        },
        {
            "id": 5,
            "coord": [
                48.582548535343214,
                65.1420117885684
            ],
            "demand": 49,
            "type": "LINEHAUL",
            "tw_h": [
                4.000649768995917,
                5.021962851559445
            ]
        },
        {
            "id": 6,
            "coord": [
                60.05457719326384,
                2.3423070139407587
            ],
            "demand": 7,
            "type": "LINEHAUL",
            "tw_h": [
                2.8347965019366246,
                5.228718301532138
            ]
        },
        {
            "id": 7,
            "coord": [
                32.845835701034645,
                82.02686531195772
            ],
            "demand": 36,
            "type": "LINEHAUL",
            "tw_h": [
                7.912905758991447,
                9.671815360431275
            ]
        },
        {
            "id": 8,
            "coord": [
                44.130426649227886,
                23.668364235238272
            ],
            "demand": 10,
            "type": "LINEHAUL",
            "tw_h": [
                20.694581544947695,
                21.87119628996226
            ]
        },
        {
            "id": 9,
            "coord": [
                41.80542497562366,
                93.072888435161
            ],
            "demand": 8,
            "type": "LINEHAUL",
            "tw_h": [
                9.387415227629702,
                10.447348670004805
            ]
        },
        {
            "id": 10,
            "coord": [
                16.710274876259636,
                75.95950701336443
            ],
            "demand": 20,
            "type": "LINEHAUL",
            "tw_h": [
                14.91423371521685,
                16.903549569201083
            ]
        },
        {
            "id": 11,
            "coord": [
                12.320216800466477,
                66.88538728337862
            ],
            "demand": 10,
            "type": "LINEHAUL",
            "tw_h": [
                9.829906053672019,
                11.274079091497264
            ]
        },
        {
            "id": 12,
            "coord": [
                70.13925324106032,
                65.79062373590733
            ],
            "demand": -47,
            "type": "BACKHAUL",
            "tw_h": [
                12.871910377237981,
                13.367770036091938
            ]
        },
        {
            "id": 13,
            "coord": [
                77.098405485997,
                93.50509130949497
            ],
            "demand": 39,
            "type": "LINEHAUL",
            "tw_h": [
                4.313070749358223,
                6.498740971192367
            ]
        },
        {
            "id": 14,
            "coord": [
                42.93584569274979,
                26.51323534570843
            ],
            "demand": -32,
            "type": "BACKHAUL",
            "tw_h": [
                2.406683928667152,
                3.5062638043082592
            ]
        },
        {
            "id": 15,
            "coord": [
                21.279722097514753,
                21.411740981383776
            ],
            "demand": -2,
            "type": "BACKHAUL",
            "tw_h": [
                19.243112884272918,
                21.75981909323247
            ]
        },
        {
            "id": 16,
            "coord": [
                52.30226681118315,
                10.497848844333957
            ],
            "demand": -24,
            "type": "BACKHAUL",
            "tw_h": [
                6.054523508825028,
                7.285501957127248
            ]
        },
        {
            "id": 17,
            "coord": [
                2.346060551275053,
                11.26333956140556
            ],
            "demand": 4,
            "type": "LINEHAUL",
            "tw_h": [
                22.161554051420275,
                23.773124055763137
            ]
        },
        {
            "id": 18,
            "coord": [
                20.72798909245198,
                5.892673848132324
            ],
            "demand": -46,
            "type": "BACKHAUL",
            "tw_h": [
                23.79738048461656,
                24.591286888898843
            ]
        },
        {
            "id": 19,
            "coord": [
                64.11657378033124,
                60.72669163004212
            ],
            "demand": 5,
            "type": "LINEHAUL",
            "tw_h": [
                20.17781229519583,
                20.232285255312522
            ]
        },
        {
            "id": 20,
            "coord": [
                93.13145448317624,
                27.696122450938542
            ],
            "demand": -45,
            "type": "BACKHAUL",
            "tw_h": [
                16.021861456803038,
                18.95548477192598
            ]
        },
        {
            "id": 21,
            "coord": [
                61.51073085961,
                65.44909723941456
            ],
            "demand": 41,
            "type": "LINEHAUL",
            "tw_h": [
                13.142177667139645,
                14.056399352277815
            ]
        },
        {
            "id": 22,
            "coord": [
                31.901097268864387,
                7.453701200946838
            ],
            "demand": -24,
            "type": "BACKHAUL",
            "tw_h": [
                21.930709758899525,
                25.385644451596647
            ]
        },
        {
            "id": 23,
            "coord": [
                70.48992720963516,
                85.53561680342847
            ],
            "demand": -12,
            "type": "BACKHAUL",
            "tw_h": [
                4.303773855063413,
                5.911794062282426
            ]
        },
        {
            "id": 24,
            "coord": [
                30.447115295808313,
                22.877937017441987
            ],
            "demand": -19,
            "type": "BACKHAUL",
            "tw_h": [
                0.9567746290065084,
                1.9060021543188022
            ]
        },
        {
            "id": 25,
            "coord": [
                29.18099166438478,
                77.93826807811861
            ],
            "demand": 28,
            "type": "LINEHAUL",
            "tw_h": [
                3.4822145930826744,
                3.9009819107871255
            ]
        },
        {
            "id": 26,
            "coord": [
                42.50255589267152,
                6.796954035178282
            ],
            "demand": -18,
            "type": "BACKHAUL",
            "tw_h": [
                14.996075292048769,
                15.273917736991523
            ]
        },
        {
            "id": 27,
            "coord": [
                12.000147953512275,
                36.729145884222746
            ],
            "demand": 40,
            "type": "LINEHAUL",
            "tw_h": [
                3.6961702236757317,
                3.725740194643069
            ]
        },
        {
            "id": 28,
            "coord": [
                33.418537826171026,
                7.714918630907686
            ],
            "demand": 13,
            "type": "LINEHAUL",
            "tw_h": [
                19.524929290850668,
                20.355083056974483
            ]
        },
        {
            "id": 29,
            "coord": [
                71.34677206004348,
                13.417031410846292
            ],
            "demand": -3,
            "type": "BACKHAUL",
            "tw_h": [
                1.7349016913826247,
                3.7076838042659475
            ]
        },
        {
            "id": 30,
            "coord": [
                53.143228451361445,
                37.22088215109329
            ],
            "demand": 2,
            "type": "LINEHAUL",
            "tw_h": [
                17.221709385737086,
                17.844053383182693
            ]
        },
        {
            "id": 31,
            "coord": [
                69.81661704331152,
                81.95981831515306
            ],
            "demand": -14,
            "type": "BACKHAUL",
            "tw_h": [
                13.138010587408665,
                14.645735630182923
            ]
        },
        {
            "id": 32,
            "coord": [
                46.08727584289144,
                37.33770766973633
            ],
            "demand": 12,
            "type": "LINEHAUL",
            "tw_h": [
                17.26990922060059,
                17.578303621882064
            ]
        },
        {
            "id": 33,
            "coord": [
                89.60178830631533,
                52.205260170526394
            ],
            "demand": -6,
            "type": "BACKHAUL",
            "tw_h": [
                20.223016219709805,
                22.287085858652407
            ]
        },
        {
            "id": 34,
            "coord": [
                93.99634590927909,
                0.6066154016841074
            ],
            "demand": -1,
            "type": "BACKHAUL",
            "tw_h": [
                20.59648273255265,
                25.014582351303837
            ]
        },
        {
            "id": 35,
            "coord": [
                32.28902069328819,
                96.23571042891558
            ],
            "demand": 30,
            "type": "LINEHAUL",
            "tw_h": [
                20.151366857203385,
                22.079228409033863
            ]
        },
        {
            "id": 36,
            "coord": [
                65.24770446670804,
                6.4883151858057815
            ],
            "demand": -3,
            "type": "BACKHAUL",
            "tw_h": [
                12.53620321403976,
                15.073254925967294
            ]
        },
        {
            "id": 37,
            "coord": [
                19.409584101677712,
                56.93695763203662
            ],
            "demand": 27,
            "type": "LINEHAUL",
            "tw_h": [
                13.89769770829222,
                13.963379052364798
            ]
        },
        {
            "id": 38,
            "coord": [
                76.30644363110423,
                41.48356798124851
            ],
            "demand": -6,
            "type": "BACKHAUL",
            "tw_h": [
                22.0060846250289,
                22.418952348835703
            ]
        },
        {
            "id": 39,
            "coord": [
                75.24338408251234,
                27.293068438484845
            ],
            "demand": 48,
            "type": "LINEHAUL",
            "tw_h": [
                11.626036563037626,
                12.778026265317665
            ]
        },
        {
            "id": 40,
            "coord": [
                62.26167840507997,
                73.96414577100613
            ],
            "demand": 12,
            "type": "LINEHAUL",
            "tw_h": [
                2.238956664692415,
                3.406416268296276
            ]
        },
        {
            "id": 41,
            "coord": [
                82.57969865121265,
                27.605725230730737
            ],
            "demand": -2,
            "type": "BACKHAUL",
            "tw_h": [
                14.167674080313603,
                16.57855964290808
            ]
        },
        {
            "id": 42,
            "coord": [
                10.641992286305314,
                23.131659758329626
            ],
            "demand": -19,
            "type": "BACKHAUL",
            "tw_h": [
                14.691995796986138,
                15.787715405352763
            ]
        },
        {
            "id": 43,
            "coord": [
                21.055744609504046,
                30.00501163195468
            ],
            "demand": 25,
            "type": "LINEHAUL",
            "tw_h": [
                13.55801560862794,
                16.08874316175295
            ]
        },
        {
            "id": 44,
            "coord": [
                0.9288232825748755,
                79.20486689870053
            ],
            "demand": 15,
            "type": "LINEHAUL",
            "tw_h": [
                15.279768718541533,
                18.8936216362742
            ]
        },
        {
            "id": 45,
            "coord": [
                26.931269115031565,
                97.44535242930226
            ],
            "demand": -36,
            "type": "BACKHAUL",
            "tw_h": [
                0.2715864332162683,
                3.000105623860738
            ]
        },
        {
            "id": 46,
            "coord": [
                88.19361393516256,
                13.968683087092849
            ],
            "demand": 17,
            "type": "LINEHAUL",
            "tw_h": [
                5.069324076071131,
                5.710452590549824
            ]
        },
        {
            "id": 47,
            "coord": [
                21.38194849659183,
                89.00469767910725
            ],
            "demand": 26,
            "type": "LINEHAUL",
            "tw_h": [
                7.94880751515725,
                8.594094595094221
            ]
        },
        {
            "id": 48,
            "coord": [
                30.71816163069596,
                95.49900585439393
            ],
            "demand": -46,
            "type": "BACKHAUL",
            "tw_h": [
                2.0570376252055897,
                2.839223580701537
            ]
        },
        {
            "id": 49,
            "coord": [
                15.124345194078648,
                68.31866677614282
            ],
            "demand": 42,
            "type": "LINEHAUL",
            "tw_h": [
                5.5298614845799925,
                6.266838070136973
            ]
        },
        {
            "id": 50,
            "coord": [
                28.642630992859463,
                71.15478170691333
            ],
            "demand": -22,
            "type": "BACKHAUL",
            "tw_h": [
                19.172894541237593,
                19.360455193963926
            ]
        },
        {
            "id": 51,
            "coord": [
                22.085481255670036,
                88.47371080348125
            ],
            "demand": 36,
            "type": "LINEHAUL",
            "tw_h": [
                4.804050676603102,
                4.998852417658024
            ]
        },
        {
            "id": 52,
            "coord": [
                25.75441961126511,
                13.443432591705262
            ],
            "demand": -46,
            "type": "BACKHAUL",
            "tw_h": [
                12.149648256108453,
                12.903404177263287
            ]
        },
        {
            "id": 53,
            "coord": [
                10.268869132070279,
                59.52099016409248
            ],
            "demand": -13,
            "type": "BACKHAUL",
            "tw_h": [
                12.738894745240728,
                13.467409727691212
            ]
        },
        {
            "id": 54,
            "coord": [
                76.89983327914199,
                30.49981473318445
            ],
            "demand": -37,
            "type": "BACKHAUL",
            "tw_h": [
                4.716609068361828,
                5.932502705636412
            ]
        },
        {
            "id": 55,
            "coord": [
                15.100365683951056,
                14.454302559332287
            ],
            "demand": 46,
            "type": "LINEHAUL",
            "tw_h": [
                1.7193826795317682,
                5.024358402651416
            ]
        },
        {
            "id": 56,
            "coord": [
                38.87297087414385,
                31.208918681617604
            ],
            "demand": -5,
            "type": "BACKHAUL",
            "tw_h": [
                13.501680330115054,
                14.149134882390442
            ]
        },
        {
            "id": 57,
            "coord": [
                61.8477750568543,
                1.0789321725891088
            ],
            "demand": -40,
            "type": "BACKHAUL",
            "tw_h": [
                13.195705903415567,
                16.771993664415692
            ]
        },
        {
            "id": 58,
            "coord": [
                8.256381247880073,
                64.56349855001181
            ],
            "demand": -17,
            "type": "BACKHAUL",
            "tw_h": [
                11.864277551644104,
                13.171260467792735
            ]
        },
        {
            "id": 59,
            "coord": [
                56.26875911225001,
                91.02650521913654
            ],
            "demand": -34,
            "type": "BACKHAUL",
            "tw_h": [
                5.204084502457903,
                6.388127354353213
            ]
        },
        {
            "id": 60,
            "coord": [
                97.68226287816543,
                96.59032312130032
            ],
            "demand": -44,
            "type": "BACKHAUL",
            "tw_h": [
                18.57063172723237,
                21.635633612232617
            ]
        },
        {
            "id": 61,
            "coord": [
                58.54517660385196,
                26.25159423258593
            ],
            "demand": 16,
            "type": "LINEHAUL",
            "tw_h": [
                6.617464376450917,
                8.31829539015648
            ]
        },
        {
            "id": 62,
            "coord": [
                36.697891858328205,
                48.93737427328648
            ],
            "demand": -14,
            "type": "BACKHAUL",
            "tw_h": [
                3.2003512686949573,
                3.556474517286096
            ]
        },
        {
            "id": 63,
            "coord": [
                72.4657736646413,
                63.3294743595023
            ],
            "demand": 49,
            "type": "LINEHAUL",
            "tw_h": [
                18.626858457051327,
                20.41981760323223
            ]
        },
        {
            "id": 64,
            "coord": [
                70.29945656584614,
                83.17486531255248
            ],
            "demand": 15,
            "type": "LINEHAUL",
            "tw_h": [
                11.020553466249897,
                11.052994929097801
            ]
        },
        {
            "id": 65,
            "coord": [
                88.14179610832458,
                28.921891424723846
            ],
            "demand": -41,
            "type": "BACKHAUL",
            "tw_h": [
                13.459819126754434,
                14.85563894690505
            ]
        },
        {
            "id": 66,
            "coord": [
                83.24527859620055,
                56.53835634065341
            ],
            "demand": 31,
            "type": "LINEHAUL",
            "tw_h": [
                0.7064127198463277,
                1.592763283433266
            ]
        },
        {
            "id": 67,
            "coord": [
                69.51989497665278,
                91.95065699689077
            ],
            "demand": 31,
            "type": "LINEHAUL",
            "tw_h": [
                21.169782838863615,
                21.29964730708259
            ]
        },
        {
            "id": 68,
            "coord": [
                21.087861346732815,
                86.75541717102608
            ],
            "demand": 45,
            "type": "LINEHAUL",
            "tw_h": [
                4.271970599437582,
                4.858073643003408
            ]
        },
        {
            "id": 69,
            "coord": [
                53.020477576044954,
                50.00498825194697
            ],
            "demand": -5,
            "type": "BACKHAUL",
            "tw_h": [
                19.146215580173486,
                19.215873782444007
            ]
        },
        {
            "id": 70,
            "coord": [
                18.313794338139544,
                4.962418286410997
            ],
            "demand": 31,
            "type": "LINEHAUL",
            "tw_h": [
                16.429610084451262,
                19.218036293323667
            ]
        },
        {
            "id": 71,
            "coord": [
                31.440012477304425,
                54.22554530785104
            ],
            "demand": 24,
            "type": "LINEHAUL",
            "tw_h": [
                0.28948975748746264,
                0.9147256119768401
            ]
        },
        {
            "id": 72,
            "coord": [
                64.90983990362443,
                29.888628381712344
            ],
            "demand": 5,
            "type": "LINEHAUL",
            "tw_h": [
                2.857871576140698,
                4.358986962958324
            ]
        },
        {
            "id": 73,
            "coord": [
                15.025084131462707,
                15.996708608396348
            ],
            "demand": -21,
            "type": "BACKHAUL",
            "tw_h": [
                11.743524868809098,
                13.091578684446718
            ]
        },
        {
            "id": 74,
            "coord": [
                13.624218744234984,
                31.056335306911855
            ],
            "demand": 24,
            "type": "LINEHAUL",
            "tw_h": [
                19.4981392074571,
                22.02752230215662
            ]
        },
        {
            "id": 75,
            "coord": [
                63.756630093590125,
                38.545066554458096
            ],
            "demand": 49,
            "type": "LINEHAUL",
            "tw_h": [
                1.6371932518709214,
                1.7645240434014557
            ]
        },
        {
            "id": 76,
            "coord": [
                28.648992752391887,
                83.42449559531703
            ],
            "demand": 7,
            "type": "LINEHAUL",
            "tw_h": [
                7.752568209905577,
                8.683309366766906
            ]
        },
        {
            "id": 77,
            "coord": [
                63.88854697026437,
                63.04177963131971
            ],
            "demand": 36,
            "type": "LINEHAUL",
            "tw_h": [
                10.580342688502009,
                11.191143205922115
            ]
        },
        {
            "id": 78,
            "coord": [
                95.54492765254302,
                90.85971846222665
            ],
            "demand": 49,
            "type": "LINEHAUL",
            "tw_h": [
                23.336926907343834,
                26.417498907283562
            ]
        },
        {
            "id": 79,
            "coord": [
                7.977062439904115,
                16.506384807999485
            ],
            "demand": 41,
            "type": "LINEHAUL",
            "tw_h": [
                23.073071159240772,
                25.564985562113286
            ]
        },
        {
            "id": 80,
            "coord": [
                35.713492505882385,
                41.446675614893145
            ],
            "demand": -34,
            "type": "BACKHAUL",
            "tw_h": [
                5.608323481871562,
                6.317186744225659
            ]
        },
        {
            "id": 81,
            "coord": [
                55.11655987533306,
                4.78901199134274
            ],
            "demand": 23,
            "type": "LINEHAUL",
            "tw_h": [
                3.838579792834296,
                5.832005491761464
            ]
        },
        {
            "id": 82,
            "coord": [
                61.888385564446565,
                70.19769700304444
            ],
            "demand": -34,
            "type": "BACKHAUL",
            "tw_h": [
                3.425931333377405,
                5.062071841748184
            ]
        },
        {
            "id": 83,
            "coord": [
                88.94115720987436,
                63.95361219915109
            ],
            "demand": 5,
            "type": "LINEHAUL",
            "tw_h": [
                7.279489442609555,
                10.05411416592171
            ]
        },
        {
            "id": 84,
            "coord": [
                31.36062106341112,
                77.62646603249455
            ],
            "demand": 15,
            "type": "LINEHAUL",
            "tw_h": [
                5.284729745365412,
                5.804267526848097
            ]
        },
        {
            "id": 85,
            "coord": [
                63.354320085356164,
                7.163988157960044
            ],
            "demand": 48,
            "type": "LINEHAUL",
            "tw_h": [
                5.9092615610218555,
                8.680861753211946
            ]
        },
        {
            "id": 86,
            "coord": [
                5.525784336906126,
                88.52833989015471
            ],
            "demand": 33,
            "type": "LINEHAUL",
            "tw_h": [
                19.87072858599788,
                23.159162089121416
            ]
        },
        {
            "id": 87,
            "coord": [
                28.54464934876755,
                23.14476637719858
            ],
            "demand": 4,
            "type": "LINEHAUL",
            "tw_h": [
                13.796731321049315,
                14.172614686707368
            ]
        },
        {
            "id": 88,
            "coord": [
                82.79096623184736,
                61.04156344503245
            ],
            "demand": -40,
            "type": "BACKHAUL",
            "tw_h": [
                5.724738073707694,
                5.809201888188092
            ]
        },
        {
            "id": 89,
            "coord": [
                8.51678610935661,
                54.90007563473752
            ],
            "demand": 8,
            "type": "LINEHAUL",
            "tw_h": [
                22.32955247122188,
                22.73048021232881
            ]
        },
        {
            "id": 90,
            "coord": [
                94.59491175754864,
                51.698267025534264
            ],
            "demand": -24,
            "type": "BACKHAUL",
            "tw_h": [
                17.177040467172674,
                17.17958954112664
            ]
        },
        {
            "id": 91,
            "coord": [
                43.109091320557425,
                25.038054107770346
            ],
            "demand": -27,
            "type": "BACKHAUL",
            "tw_h": [
                6.832782568562084,
                8.004317142372935
            ]
        },
        {
            "id": 92,
            "coord": [
                43.821124223984306,
                64.78613936561133
            ],
            "demand": -41,
            "type": "BACKHAUL",
            "tw_h": [
                4.38540319387176,
                4.469176737509805
            ]
        },
        {
            "id": 93,
            "coord": [
                36.883479299337885,
                46.38445232664103
            ],
            "demand": 26,
            "type": "LINEHAUL",
            "tw_h": [
                21.50079004271691,
                21.79373025268889
            ]
        },
        {
            "id": 94,
            "coord": [
                62.851400677482374,
                39.34990795018939
            ],
            "demand": -5,
            "type": "BACKHAUL",
            "tw_h": [
                0.1582615846238271,
                1.0400509496428114
            ]
        },
        {
            "id": 95,
            "coord": [
                21.00512562589143,
                32.36194830888602
            ],
            "demand": -49,
            "type": "BACKHAUL",
            "tw_h": [
                23.74163170408,
                25.12932053042584
            ]
        },
        {
            "id": 96,
            "coord": [
                33.605748865831075,
                42.14104746574071
            ],
            "demand": -49,
            "type": "BACKHAUL",
            "tw_h": [
                0.8438143991245051,
                1.4132029942916218
            ]
        },
        {
            "id": 97,
            "coord": [
                15.3727056867761,
                71.06722095684464
            ],
            "demand": 23,
            "type": "LINEHAUL",
            "tw_h": [
                14.623106636422637,
                15.367003296892726
            ]
        },
        {
            "id": 98,
            "coord": [
                91.70788303876834,
                19.902526234955285
            ],
            "demand": -22,
            "type": "BACKHAUL",
            "tw_h": [
                10.009210712498716,
                12.869606917520699
            ]
        },
        {
            "id": 99,
            "coord": [
                37.79904229324509,
                98.55068931027547
            ],
            "demand": 4,
            "type": "LINEHAUL",
            "tw_h": [
                15.782693919464524,
                18.903932533346882
            ]
        },
        {
            "id": 100,
            "coord": [
                88.26495260813132,
                95.20423301190478
            ],
            "demand": -37,
            "type": "BACKHAUL",
            "tw_h": [
                22.80756232058605,
                25.112296693484474
            ]
        },
        {
            "id": 101,
            "coord": [
                32.2390871883523,
                36.484377961085414
            ],
            "demand": -31,
            "type": "BACKHAUL",
            "tw_h": [
                23.544932987354784,
                23.741617982985503
            ]
        },
        {
            "id": 102,
            "coord": [
                20.087699483748523,
                27.716612259579286
            ],
            "demand": -35,
            "type": "BACKHAUL",
            "tw_h": [
                12.421494467251058,
                14.311304470504723
            ]
        },
        {
            "id": 103,
            "coord": [
                67.18790700771001,
                80.39694415095533
            ],
            "demand": -4,
            "type": "BACKHAUL",
            "tw_h": [
                22.28574082588162,
                23.517383483118145
            ]
        },
        {
            "id": 104,
            "coord": [
                85.402725897842,
                70.98237247487734
            ],
            "demand": 21,
            "type": "LINEHAUL",
            "tw_h": [
                10.478059116253764,
                13.23012325924493
            ]
        },
        {
            "id": 105,
            "coord": [
                56.428206270354956,
                95.69354127018642
            ],
            "demand": -24,
            "type": "BACKHAUL",
            "tw_h": [
                11.287735587781121,
                11.48769064302084
            ]
        },
        {
            "id": 106,
            "coord": [
                93.24168603380588,
                78.85833759519284
            ],
            "demand": 6,
            "type": "LINEHAUL",
            "tw_h": [
                10.83542736255553,
                11.888183477894984
            ]
        },
        {
            "id": 107,
            "coord": [
                45.70930612750579,
                94.04683916152447
            ],
            "demand": 1,
            "type": "LINEHAUL",
            "tw_h": [
                15.741624997610801,
                18.451089065703947
            ]
        },
        {
            "id": 108,
            "coord": [
                95.03172368332052,
                21.816594159239266
            ],
            "demand": -11,
            "type": "BACKHAUL",
            "tw_h": [
                1.129495274722455,
                2.3910174353772984
            ]
        },
        {
            "id": 109,
            "coord": [
                62.61824017691969,
                69.61049216682201
            ],
            "demand": -37,
            "type": "BACKHAUL",
            "tw_h": [
                21.59143361496883,
                23.00674288331741
            ]
        },
        {
            "id": 110,
            "coord": [
                28.86025203696643,
                51.92973635140502
            ],
            "demand": 29,
            "type": "LINEHAUL",
            "tw_h": [
                18.801271348901615,
                19.42068600055317
            ]
        },
        {
            "id": 111,
            "coord": [
                55.86665831860661,
                11.087173539046768
            ],
            "demand": -18,
            "type": "BACKHAUL",
            "tw_h": [
                22.9020835751388,
                25.40587781457948
            ]
        },
        {
            "id": 112,
            "coord": [
                49.785976281291674,
                18.778033069822364
            ],
            "demand": -37,
            "type": "BACKHAUL",
            "tw_h": [
                19.653145315967006,
                20.926139148340535
            ]
        },
        {
            "id": 113,
            "coord": [
                24.305990039851764,
                73.84020973832067
            ],
            "demand": 7,
            "type": "LINEHAUL",
            "tw_h": [
                15.387155362372699,
                15.733899870886889
            ]
        },
        {
            "id": 114,
            "coord": [
                2.3256537166134628,
                0.4469368708938548
            ],
            "demand": -39,
            "type": "BACKHAUL",
            "tw_h": [
                0.8490996310235444,
                0.9255852513717681
            ]
        },
        {
            "id": 115,
            "coord": [
                63.293589477298404,
                28.139070108122876
            ],
            "demand": 40,
            "type": "LINEHAUL",
            "tw_h": [
                1.2984092033562806,
                2.2766961193872772
            ]
        },
        {
            "id": 116,
            "coord": [
                91.45873109231046,
                25.57448083801066
            ],
            "demand": -42,
            "type": "BACKHAUL",
            "tw_h": [
                22.677680660762356,
                24.754639236777244
            ]
        },
        {
            "id": 117,
            "coord": [
                67.53055610846299,
                41.59471503698345
            ],
            "demand": 23,
            "type": "LINEHAUL",
            "tw_h": [
                18.911387778898366,
                20.0115038949686
            ]
        },
        {
            "id": 118,
            "coord": [
                46.759506284109975,
                84.41959109916898
            ],
            "demand": -8,
            "type": "BACKHAUL",
            "tw_h": [
                22.66585690450553,
                23.382904602269097
            ]
        },
        {
            "id": 119,
            "coord": [
                48.73315194078801,
                74.01487273158402
            ],
            "demand": -5,
            "type": "BACKHAUL",
            "tw_h": [
                11.931090131046627,
                13.59890247456311
            ]
        },
        {
            "id": 120,
            "coord": [
                88.61636555692634,
                14.933630165628509
            ],
            "demand": 27,
            "type": "LINEHAUL",
            "tw_h": [
                7.922735395774944,
                10.653135779963325
            ]
        },
        {
            "id": 121,
            "coord": [
                70.92355530149128,
                79.51440173368576
            ],
            "demand": 30,
            "type": "LINEHAUL",
            "tw_h": [
                9.90130351533696,
                10.31686772190176
            ]
        },
        {
            "id": 122,
            "coord": [
                4.947954696908274,
                2.5784233834860504
            ],
            "demand": 7,
            "type": "LINEHAUL",
            "tw_h": [
                4.875326215006791,
                6.640673660150366
            ]
        },
        {
            "id": 123,
            "coord": [
                8.920084189587596,
                4.8823217248401
            ],
            "demand": -50,
            "type": "BACKHAUL",
            "tw_h": [
                0.6912036320720976,
                4.726923075394829
            ]
        },
        {
            "id": 124,
            "coord": [
                47.49782092041015,
                24.237993009144155
            ],
            "demand": 34,
            "type": "LINEHAUL",
            "tw_h": [
                8.526642880565042,
                8.99412912876149
            ]
        },
        {
            "id": 125,
            "coord": [
                12.87831403775417,
                33.79860555967561
            ],
            "demand": 1,
            "type": "LINEHAUL",
            "tw_h": [
                19.20579489625312,
                19.22289373416578
            ]
        },
        {
            "id": 126,
            "coord": [
                83.99738395930756,
                28.000955235101664
            ],
            "demand": -38,
            "type": "BACKHAUL",
            "tw_h": [
                18.28738369713208,
                19.65420898583862
            ]
        },
        {
            "id": 127,
            "coord": [
                6.886830906858665,
                62.4999115016833
            ],
            "demand": -31,
            "type": "BACKHAUL",
            "tw_h": [
                2.1586505327927803,
                3.49761504455154
            ]
        },
        {
            "id": 128,
            "coord": [
                66.10581983612957,
                25.102431512291055
            ],
            "demand": -2,
            "type": "BACKHAUL",
            "tw_h": [
                23.666764771239205,
                23.754772501515298
            ]
        },
        {
            "id": 129,
            "coord": [
                73.05944171075681,
                6.414249259424476
            ],
            "demand": -26,
            "type": "BACKHAUL",
            "tw_h": [
                6.818598558287759,
                7.477403556002052
            ]
        },
        {
            "id": 130,
            "coord": [
                76.13667420813186,
                73.5326039677162
            ],
            "demand": -3,
            "type": "BACKHAUL",
            "tw_h": [
                14.20027042792428,
                14.725021109961672
            ]
        },
        {
            "id": 131,
            "coord": [
                9.37500453973118,
                78.96572837490635
            ],
            "demand": -22,
            "type": "BACKHAUL",
            "tw_h": [
                20.362239508362997,
                21.72591985056157
            ]
        },
        {
            "id": 132,
            "coord": [
                36.6143646690541,
                41.5055204918364
            ],
            "demand": 21,
            "type": "LINEHAUL",
            "tw_h": [
                22.80596260501099,
                22.95037668443266
            ]
        },
        {
            "id": 133,
            "coord": [
                96.03333787533181,
                13.23344270881428
            ],
            "demand": 1,
            "type": "LINEHAUL",
            "tw_h": [
                5.515782345626662,
                5.633974840140896
            ]
        },
        {
            "id": 134,
            "coord": [
                33.857364234481324,
                0.3112646202190872
            ],
            "demand": 45,
            "type": "LINEHAUL",
            "tw_h": [
                1.0686217504686697,
                1.7875034416019364
            ]
        },
        {
            "id": 135,
            "coord": [
                68.10350046788027,
                2.993510269609967
            ],
            "demand": -10,
            "type": "BACKHAUL",
            "tw_h": [
                14.10217410065098,
                16.182104033144952
            ]
        },
        {
            "id": 136,
            "coord": [
                81.6454825243705,
                74.99139871582021
            ],
            "demand": -42,
            "type": "BACKHAUL",
            "tw_h": [
                17.430313048120613,
                18.13765690311665
            ]
        },
        {
            "id": 137,
            "coord": [
                24.618904577632062,
                86.00921861634076
            ],
            "demand": -14,
            "type": "BACKHAUL",
            "tw_h": [
                14.374152783577584,
                17.626917078094515
            ]
        },
        {
            "id": 138,
            "coord": [
                86.79523001146106,
                8.793525328946583
            ],
            "demand": 1,
            "type": "LINEHAUL",
            "tw_h": [
                7.710842006082027,
                8.685309182985126
            ]
        },
        {
            "id": 139,
            "coord": [
                7.6573345408044275,
                26.603935673408287
            ],
            "demand": -17,
            "type": "BACKHAUL",
            "tw_h": [
                4.456379765005389,
                7.958397210414896
            ]
        },
        {
            "id": 140,
            "coord": [
                49.50350816677256,
                26.442077968170775
            ],
            "demand": -17,
            "type": "BACKHAUL",
            "tw_h": [
                15.277757438297062,
                16.150861557237345
            ]
        },
        {
            "id": 141,
            "coord": [
                2.46475419308968,
                89.74914915049209
            ],
            "demand": -22,
            "type": "BACKHAUL",
            "tw_h": [
                11.895153161012338,
                12.26504418392401
            ]
        },
        {
            "id": 142,
            "coord": [
                45.8993558773527,
                58.051169860199906
            ],
            "demand": -15,
            "type": "BACKHAUL",
            "tw_h": [
                5.408380134658099,
                5.882543284627675
            ]
        },
        {
            "id": 143,
            "coord": [
                42.9788411483952,
                7.08223237612563
            ],
            "demand": -22,
            "type": "BACKHAUL",
            "tw_h": [
                6.040754729879527,
                7.716426452331009
            ]
        },
        {
            "id": 144,
            "coord": [
                23.20107754856383,
                47.769962091509434
            ],
            "demand": 29,
            "type": "LINEHAUL",
            "tw_h": [
                21.70117996303277,
                22.070531891873504
            ]
        },
        {
            "id": 145,
            "coord": [
                24.487116715964262,
                10.170167881495463
            ],
            "demand": 31,
            "type": "LINEHAUL",
            "tw_h": [
                11.334339479218263,
                14.039296873006336
            ]
        },
        {
            "id": 146,
            "coord": [
                42.97675835161164,
                43.0138852786346
            ],
            "demand": -45,
            "type": "BACKHAUL",
            "tw_h": [
                17.858772190509534,
                18.472732089955407
            ]
        },
        {
            "id": 147,
            "coord": [
                21.776916841281878,
                1.2621577683030405
            ],
            "demand": -46,
            "type": "BACKHAUL",
            "tw_h": [
                21.85323161628349,
                24.292376951141275
            ]
        },
        {
            "id": 148,
            "coord": [
                38.15828327483414,
                90.21309743706216
            ],
            "demand": -14,
            "type": "BACKHAUL",
            "tw_h": [
                5.418320010137613,
                7.0202948272723065
            ]
        },
        {
            "id": 149,
            "coord": [
                56.88989336421512,
                1.0952276486867363
            ],
            "demand": 18,
            "type": "LINEHAUL",
            "tw_h": [
                22.24802041191323,
                22.98265187977951
            ]
        },
        {
            "id": 150,
            "coord": [
                27.392519487009015,
                38.10794199337757
            ],
            "demand": 29,
            "type": "LINEHAUL",
            "tw_h": [
                7.052231552545672,
                7.430320093702651
            ]
        }
    ]
}