{
    "Config": {
        "General": {
            "NUM_CUSTOMERS": 20,
            "NUM_NODES": 21,
            "MAX_COORD_KM": 100,
            "T_MAX_SYSTEM_H": 78.45213739863443,
            "TIME_WINDOW_SCALING_FACTOR": 1.5,
            "COORD_DISTRIBUTION": "multi-gaussian",
            "NUM_CLUSTERS": 3
        },
        "Vehicles": {
            "NUM_TRUCKS": 4,
            "NUM_DRONES": 4,
            "V_TRUCK_KM_H": 40.0,
            "V_DRONE_KM_H": 60.0,
            "CAPACITY_TRUCK": 200,
            "CAPACITY_DRONE": 50,
            "DRONE_TAKEOFF_MIN": 1.0,
            "DRONE_LANDING_MIN": 1.0,
            "SERVICE_TIME_MIN": 5.0,
            "DRONE_DURATION_H": 1.0
        },
        "Depot": {
            "id": 0,
            "coord": [
                0.0,
                0.0
            ],
            "time_window_h": [
                0.0,
                78.45213739863443
            ]
        }
    },
    "Nodes": [
        {
            "id": 1,
            "coord": [
                21.439774359068434,
                100.0
            ],
            "demand": -28,
            "type": "BACKHAUL",
            "tw_h": [
                0.9252441440971211,
                6.265589212191695
            ]
        },
        {
            "id": 2,
            "coord": [
                33.99986489638037,
                94.64251561968955
            ],
            "demand": -8,
            "type": "BACKHAUL",
            "tw_h": [
                3.4543973134886645,
                6.94296787500585
            ]
        },
        {
            "id": 3,
            "coord": [
                2.422594508891537,
                59.114603938022775
            ],
            "demand": -26,
            "type": "BACKHAUL",
            "tw_h": [
                16.119522338826407,
                19.63809831871439
            ]
        },
        {
            "id": 4,
            "coord": [
                27.020149445972454,
                80.84212747084736
            ],
            "demand": 48,
            "type": "LINEHAUL",
            "tw_h": [
                10.876541483189097,
                14.06192579992716
            ]
        },
        {
            "id": 5,
            "coord": [
                8.315745211235033,
                33.00167993750073
            ],
            "demand": 9,
            "type": "LINEHAUL",
            "tw_h": [
                0.4597705925843467,
                1.5634405881265774
            ]
        },
        {
            "id": 6,
            "coord": [
                1.0800987895705756,
                6.528898194480984
            ],
            "demand": -26,
            "type": "BACKHAUL",
            "tw_h": [
                8.936992339702229,
                9.360002626107171
            ]
        },
        {
            "id": 7,
            "coord": [
                29.63948964012202,
                88.87353497797407
            ],
            "demand": -29,
            "type": "BACKHAUL",
            "tw_h": [
                13.127613702984135,
                18.43479094726518
            ]
        },
        {
            "id": 8,
            "coord": [
                40.79235730633081,
                83.68413565984766
            ],
            "demand": 45,
            "type": "LINEHAUL",
            "tw_h": [
                10.41763533245362,
                11.647829097549948
            ]
        },
        {
            "id": 9,
            "coord": [
                12.5567278585998,
                14.040064486344658
            ],
            "demand": -22,
            "type": "BACKHAUL",
            "tw_h": [
                20.421006043071333,
                21.57973070334662
            ]
        },
        {
            "id": 10,
            "coord": [
                0.0,
                66.57641886160454
            ],
            "demand": 24,
            "type": "LINEHAUL",
            "tw_h": [
                9.020598856234773,
                9.498666378110501
            ]
        },
        {
            "id": 11,
            "coord": [
                13.898899054243945,
                58.03636758588884
            ],
            "demand": -8,
            "type": "BACKHAUL",
            "tw_h": [
                12.2983283104614,
                14.518227986667219
            ]
        },
        {
            "id": 12,
            "coord": [
                12.05214998244411,
                67.93324404382855
            ],
            "demand": 10,
            "type": "LINEHAUL",
            "tw_h": [
                18.53522379163238,
                21.625555173278553
            ]
        },
        {
            "id": 13,
            "coord": [
                20.599087391606336,
                10.759779198103324
            ],
            "demand": -45,
            "type": "BACKHAUL",
            "tw_h": [
                12.160224307525635,
                13.162724132980678
            ]
        },
        {
            "id": 14,
            "coord": [
                6.581975020657447,
                71.58505308226071
            ],
            "demand": 25,
            "type": "LINEHAUL",
            "tw_h": [
                9.046204459106615,
                9.309956506259793
            ]
        },
        {
            "id": 15,
            "coord": [
                6.380878843684103,
                61.65063117240258
            ],
            "demand": -16,
            "type": "BACKHAUL",
            "tw_h": [
                1.469056282035,
                5.847492689171984
            ]
        },
        {
            "id": 16,
            "coord": [
                23.75652627777574,
                58.088396680424395
            ],
            "demand": 26,
            "type": "LINEHAUL",
            "tw_h": [
                20.138356834481854,
                21.532348510968582
            ]
        },
        {
            "id": 17,
            "coord": [
                23.52223372591275,
                61.59235492412191
            ],
            "demand": 34,
            "type": "LINEHAUL",
            "tw_h": [
                21.33005459494202,
                23.912507962876294
            ]
        },
        {
            "id": 18,
            "coord": [
                38.99189898419478,
                84.4617119196078
            ],
            "demand": 23,
            "type": "LINEHAUL",
            "tw_h": [
                2.472977040093795,
                8.443177181987707
            ]
        },
        {
            "id": 19,
            "coord": [
                9.219233593055698,
                61.9134487178119
            ],
            "demand": -46,
            "type": "BACKHAUL",
            "tw_h": [
                14.02504950535074,
                18.404211542613872
            ]
        },
        {
            "id": 20,
            "coord": [
                12.703803054431484,
                60.74429355774846
            ],
            "demand": 41,
            "type": "LINEHAUL",
            "tw_h": [
                16.30204028982626,
                16.7400120502499
            ]
        }
    ]
}